playwrighting/__init__.py
playwrighting/accounts.py
playwrighting/app.py
playwrighting/config.py
playwrighting/constants.py
playwrighting/exceptions.py
playwrighting/navigation/__init__.py
playwrighting/navigation/login.py
playwrighting/navigation/logout.py
playwrighting/navigation/transactions.py
playwrighting/page_selectors.py
playwrighting/pying.py
playwrighting/transactions.py
playwrighting/utils.py
playwrighting-0.8.0.dist-info/entry_points.txt
playwrighting-0.8.0.dist-info/WHEEL
playwrighting-0.8.0.dist-info/METADATA
playwrighting-0.8.0.dist-info/RECORD
