Metadata-Version: 2.1
Name: playwrighting
Version: 0.8.0
Summary: Get your ING account data
License: MIT
Author: Pablo Cabezas
Author-email: headsrooms@gmail.com
Requires-Python: >=3.9,<4.0
Classifier: License :: OSI Approved :: MIT License
Classifier: Programming Language :: Python :: 3
Classifier: Programming Language :: Python :: 3.9
Requires-Dist: 12factor-configclasses (>=0.4,<0.5)
Requires-Dist: anyio (>=3.1.0,<4.0.0)
Requires-Dist: asyncclick (>=8.0.1,<9.0.0)
Requires-Dist: beautifulsoup4 (>=4.9,<5.0)
Requires-Dist: dateparser (>=1.0.0,<2.0.0)
Requires-Dist: html5lib (>=1.1,<2.0)
Requires-Dist: lxml (>=4.6.3,<5.0.0)
Requires-Dist: more-itertools (>=8.7,<9.0)
Requires-Dist: pandas (>=1.2.4,<2.0.0)
Requires-Dist: playwright (>=1.11,<2.0)
Requires-Dist: python-dotenv (>=0.15,<0.16)
Requires-Dist: rich (>=10.2.2,<11.0.0)
Requires-Dist: selectolax (>=0.2,<0.3)
Requires-Dist: tabulate (>=0.8.9,<0.9.0)
Requires-Dist: textual (>=0.1.5,<0.2.0)
